rtl/alu_8bit.sv
module alu_8bit (
    input  logic [7:0] A,
    input  logic [7:0] B,
    input  logic [2:0] OP,

    output logic [7:0] RESULT,
    output logic       CARRY,
    output logic       ZERO,
    output logic       OVERFLOW
);

    logic [8:0] TEMP;

    always_comb begin

        // Default values
        RESULT   = 8'b0;
        CARRY    = 1'b0;
        OVERFLOW = 1'b0;
        TEMP     = 9'b0;

        case (OP)

            // ADD
            3'b000: begin
                TEMP   = {1'b0, A} + {1'b0, B};
                RESULT = TEMP[7:0];
                CARRY  = TEMP[8];

                // Signed overflow
                OVERFLOW = (~(A[7] ^ B[7])) &
                           (RESULT[7] ^ A[7]);
            end

            // SUB
            3'b001: begin
                TEMP   = {1'b0, A} - {1'b0, B};
                RESULT = TEMP[7:0];

                // CARRY = 1 means no borrow
                CARRY = (A >= B);

                // Signed overflow
                OVERFLOW = (A[7] ^ B[7]) &
                           (RESULT[7] ^ A[7]);
            end

            // AND
            3'b010: begin
                RESULT = A & B;
            end

            // OR
            3'b011: begin
                RESULT = A | B;
            end

            // XOR
            3'b100: begin
                RESULT = A ^ B;
            end

            // NOT
            3'b101: begin
                RESULT = ~A;
            end

            // Shift Left
            3'b110: begin
                RESULT = A << 1;
                CARRY  = A[7];
            end

            // Shift Right
            3'b111: begin
                RESULT = A >> 1;
                CARRY  = A[0];
            end

            default: begin
                RESULT   = 8'b0;
                CARRY    = 1'b0;
                OVERFLOW = 1'b0;
            end

        endcase

        // Zero flag
        ZERO = (RESULT == 8'b0);

    end

endmodule

tb/alu_8bit_tb.sv
module alu_8bit_tb;

    logic [7:0] A;
    logic [7:0] B;
    logic [2:0] OP;

    logic [7:0] RESULT;
    logic       CARRY;
    logic       ZERO;
    logic       OVERFLOW;

    integer errors;

    alu_8bit DUT (
        .A(A),
        .B(B),
        .OP(OP),
        .RESULT(RESULT),
        .CARRY(CARRY),
        .ZERO(ZERO),
        .OVERFLOW(OVERFLOW)
    );

    task automatic check_result(
        input [7:0] expected_result,
        input       expected_carry,
        input       expected_overflow
    );

        begin

            #1;

            if (RESULT !== expected_result) begin
                $display(
                    "ERROR: OP=%b A=%d B=%d RESULT=%d EXPECTED=%d",
                    OP, A, B, RESULT, expected_result
                );
                errors = errors + 1;
            end

            if (CARRY !== expected_carry) begin
                $display(
                    "ERROR: OP=%b A=%d B=%d CARRY=%b EXPECTED=%b",
                    OP, A, B, CARRY, expected_carry
                );
                errors = errors + 1;
            end

            if (ZERO !== (expected_result == 8'b0)) begin
                $display("ERROR: ZERO flag incorrect");
                errors = errors + 1;
            end

            if (OVERFLOW !== expected_overflow) begin
                $display("ERROR: OVERFLOW flag incorrect");
                errors = errors + 1;
            end

        end

    endtask

    initial begin

        errors = 0;

        $dumpfile("sim/alu.vcd");
        $dumpvars(0, alu_8bit_tb);

        $display("--------------------------------");
        $display("       8-BIT ALU TEST");
        $display("--------------------------------");

        // ADD
        OP = 3'b000;
        A = 8'd5;
        B = 8'd3;
        check_result(8'd8, 1'b0, 1'b0);

        A = 8'd255;
        B = 8'd1;
        check_result(8'd0, 1'b1, 1'b0);

        // SUB
        OP = 3'b001;
        A = 8'd10;
        B = 8'd3;
        check_result(8'd7, 1'b1, 1'b0);

        A = 8'd3;
        B = 8'd10;
        check_result(8'd249, 1'b0, 1'b0);

        // AND
        OP = 3'b010;
        A = 8'b10101010;
        B = 8'b11001100;
        check_result(8'b10001000, 1'b0, 1'b0);

        // OR
        OP = 3'b011;
        A = 8'b10101010;
        B = 8'b11001100;
        check_result(8'b11101110, 1'b0, 1'b0);

        // XOR
        OP = 3'b100;
        A = 8'b10101010;
        B = 8'b11001100;
        check_result(8'b01100110, 1'b0, 1'b0);

        // NOT
        OP = 3'b101;
        A = 8'b10101010;
        B = 8'b00000000;
        check_result(8'b01010101, 1'b0, 1'b0);

        // SHIFT LEFT
        OP = 3'b110;
        A = 8'b10000001;
        B = 8'b00000000;
        check_result(8'b00000010, 1'b1, 1'b0);

        // SHIFT RIGHT
        OP = 3'b111;
        A = 8'b10000001;
        B = 8'b00000000;
        check_result(8'b01000000, 1'b1, 1'b0);

        // SIGNED OVERFLOW: 127 + 1
        OP = 3'b000;
        A = 8'd127;
        B = 8'd1;
        check_result(8'b10000000, 1'b0, 1'b1);

        // SIGNED OVERFLOW: -128 - 1
        OP = 3'b001;
        A = 8'b10000000;
        B = 8'd1;
        check_result(8'b01111111, 1'b1, 1'b1);

        $display("--------------------------------");

        if (errors == 0)
            $display("ALL TESTS PASSED");
        else
            $display("TESTS FAILED: %0d errors", errors);

        $display("--------------------------------");

        $finish;

    end

endmodule

sim/alu.vcd
$date
	Tue Sep 15 18:11:17 2026
$end
$version
	Icarus Verilog
$end
$timescale
	1s
$end
$scope module alu_8bit_tb $end
$var wire 1 ! ZERO $end
$var wire 8 " RESULT [7:0] $end
$var wire 1 # OVERFLOW $end
$var wire 1 $ CARRY $end
$var reg 8 % A [7:0] $end
$var reg 8 & B [7:0] $end
$var reg 3 ' OP [2:0] $end
$var integer 32 ( errors [31:0] $end
$scope module DUT $end
$var wire 8 ) A [7:0] $end
$var wire 8 * B [7:0] $end
$var wire 3 + OP [2:0] $end
$var reg 1 $ CARRY $end
$var reg 1 # OVERFLOW $end
$var reg 8 , RESULT [7:0] $end
$var reg 9 - TEMP [8:0] $end
$var reg 1 ! ZERO $end
$upscope $end
$scope task check_result $end
$upscope $end
$upscope $end
$enddefinitions $end
$comment Show the parameter values. $end
$dumpall
$end
#0
$dumpvars
b1000 -
b1000 ,
b0 +
b11 *
b101 )
b0 (
b0 '
b11 &
b101 %
0$
0#
b1000 "
0!
$end
#1
1!
1$
b100000000 -
b0 "
b0 ,
b1 &
b1 *
b11111111 %
b11111111 )
#2
0!
b111 "
b111 ,
b111 -
1$
b11 &
b11 *
b1010 %
b1010 )
b1 '
b1 +
#3
b111111001 -
0$
b11111001 "
b11111001 ,
b1010 &
b1010 *
b11 %
b11 )
#4
b0 -
b10001000 "
b10001000 ,
b11001100 &
b11001100 *
b10101010 %
b10101010 )
b10 '
b10 +
#5
b11101110 "
b11101110 ,
b11 '
b11 +
#6
b1100110 "
b1100110 ,
b100 '
b100 +
#7
b1010101 "
b1010101 ,
b0 &
b0 *
b101 '
b101 +
#8
1$
b10 "
b10 ,
b10000001 %
b10000001 )
b110 '
b110 +
#9
1$
b1000000 "
b1000000 ,
b111 '
b111 +
#10
1#
b10000000 -
0$
b10000000 "
b10000000 ,
b1 &
b1 *
b1111111 %
b1111111 )
b0 '
b0 +
#11
1$
b1111111 -
1#
b1111111 "
b1111111 ,
b10000000 %
b10000000 )
b1 '
b1 +
